spigit/gitscript.py
spigit/gitscriptconfig.json
spigit/service
spigit/serviceinstall.sh
spigit-0.1.9.data/data/spigit/gitscriptconfig.json
spigit-0.1.9.data/data/spigit/service
spigit-0.1.9.data/data/spigit/serviceinstall.sh
spigit-0.1.9.dist-info/DESCRIPTION.rst
spigit-0.1.9.dist-info/METADATA
spigit-0.1.9.dist-info/RECORD
spigit-0.1.9.dist-info/WHEEL
spigit-0.1.9.dist-info/metadata.json
spigit-0.1.9.dist-info/top_level.txt
