Metadata-Version: 2.0
Name: spigit
Version: 0.1.9
Summary: A deployment manager service.
Home-page: https://github.com/username/spigit/
Author: Taylor Halcomb
Author-email: taylortextalert@gmail.com
License: MIT
Keywords: github git server deployment service update
Platform: UNKNOWN
Requires-Dist: gitpython
